cfddb/__init__.py
cfddb/cli.py
cfddb/cfn/__init__.py
cfddb/cfn/conditions.py
cfddb/cfn/constants.py
cfddb/cfn/intrinsics.py
cfddb/cfn/parser.py
cfddb/cfn/ssm.py
cfddb/dynamodb/__init__.py
cfddb/dynamodb/client.py
cfddb/dynamodb/streams.py
cfddb/dynamodb/tables.py
cfddb/engine/__init__.py
cfddb/engine/diff.py
cfddb/engine/executor.py
cfddb/engine/plan_output.py
cfddb/engine/planner.py
cfddb/engine/state.py
cfddb-0.1.1.dist-info/METADATA
cfddb-0.1.1.dist-info/WHEEL
cfddb-0.1.1.dist-info/entry_points.txt
cfddb-0.1.1.dist-info/licenses/LICENSE
cfddb-0.1.1.dist-info/RECORD
