Metadata-Version: 2.4
Name: cfddb
Version: 0.1.1
Summary: A lightweight CloudFormation parser that interprets DynamoDB table resources and applies them to DynamoDB Local
Project-URL: Homepage, https://github.com/m-ali-ubit/cfddb
Project-URL: Repository, https://github.com/m-ali-ubit/cfddb
Project-URL: Issues, https://github.com/m-ali-ubit/cfddb/issues
Author-email: Muhammad Ali <usermalikhan@gmail.com>
License: Apache-2.0
License-File: LICENSE
Keywords: aws,cloudformation,dynamoDB,local,parser,yaml
Classifier: Intended Audience :: Developers
Classifier: Operating System :: OS Independent
Classifier: Programming Language :: Python :: 3
Classifier: Programming Language :: Python :: 3.9
Classifier: Programming Language :: Python :: 3.10
Classifier: Programming Language :: Python :: 3.11
Classifier: Programming Language :: Python :: 3.12
Classifier: Programming Language :: Python :: 3.13
Requires-Python: >=3.10
Requires-Dist: boto3>=1.28
Requires-Dist: pydantic>=2.7.1
Requires-Dist: pyyaml>=6.0
Requires-Dist: rich>=13.0
Provides-Extra: dev
Requires-Dist: build; extra == 'dev'
Requires-Dist: moto[dynamodb]; extra == 'dev'
Requires-Dist: pre-commit; extra == 'dev'
Requires-Dist: pytest; extra == 'dev'
Requires-Dist: pytest-mock; extra == 'dev'
Requires-Dist: ruff; extra == 'dev'
Requires-Dist: twine; extra == 'dev'
